{
  "version": "0.3.14-fixed",
  "steps": [
    {
      "tag": "CreateEnum",
      "enum": "QuestionType",
      "values": [
        "BOOLEAN",
        "TEXT"
      ]
    },
    {
      "tag": "CreateEnum",
      "enum": "Role",
      "values": [
        "USER",
        "ADMIN",
        "MODERATOR",
        "ORGANIZATION"
      ]
    },
    {
      "tag": "CreateEnum",
      "enum": "State",
      "values": [
        "PENDING",
        "REVIEW",
        "REJECTED",
        "APPROVED",
        "COMPLETED",
        "ARCHIVED"
      ]
    },
    {
      "tag": "CreateSource",
      "source": "db"
    },
    {
      "tag": "CreateArgument",
      "location": {
        "tag": "Source",
        "source": "db"
      },
      "argument": "provider",
      "value": "\"postgresql\""
    },
    {
      "tag": "CreateArgument",
      "location": {
        "tag": "Source",
        "source": "db"
      },
      "argument": "url",
      "value": "env(\"DATABASE_URL\")"
    },
    {
      "tag": "CreateModel",
      "model": "User"
    },
    {
      "tag": "CreateField",
      "model": "User",
      "field": "id",
      "type": "Int",
      "arity": "Required"
    },
    {
      "tag": "CreateDirective",
      "location": {
        "path": {
          "tag": "Field",
          "model": "User",
          "field": "id"
        },
        "directive": "default"
      }
    },
    {
      "tag": "CreateArgument",
      "location": {
        "tag": "Directive",
        "path": {
          "tag": "Field",
          "model": "User",
          "field": "id"
        },
        "directive": "default"
      },
      "argument": "",
      "value": "autoincrement()"
    },
    {
      "tag": "CreateDirective",
      "location": {
        "path": {
          "tag": "Field",
          "model": "User",
          "field": "id"
        },
        "directive": "id"
      }
    },
    {
      "tag": "CreateField",
      "model": "User",
      "field": "uid",
      "type": "String",
      "arity": "Required"
    },
    {
      "tag": "CreateDirective",
      "location": {
        "path": {
          "tag": "Field",
          "model": "User",
          "field": "uid"
        },
        "directive": "unique"
      }
    },
    {
      "tag": "CreateField",
      "model": "User",
      "field": "email",
      "type": "String",
      "arity": "Required"
    },
    {
      "tag": "CreateDirective",
      "location": {
        "path": {
          "tag": "Field",
          "model": "User",
          "field": "email"
        },
        "directive": "unique"
      }
    },
    {
      "tag": "CreateField",
      "model": "User",
      "field": "displayName",
      "type": "String",
      "arity": "Required"
    },
    {
      "tag": "CreateField",
      "model": "User",
      "field": "phoneNumber",
      "type": "String",
      "arity": "Optional"
    },
    {
      "tag": "CreateField",
      "model": "User",
      "field": "emailVerified",
      "type": "Boolean",
      "arity": "Required"
    },
    {
      "tag": "CreateDirective",
      "location": {
        "path": {
          "tag": "Field",
          "model": "User",
          "field": "emailVerified"
        },
        "directive": "default"
      }
    },
    {
      "tag": "CreateArgument",
      "location": {
        "tag": "Directive",
        "path": {
          "tag": "Field",
          "model": "User",
          "field": "emailVerified"
        },
        "directive": "default"
      },
      "argument": "",
      "value": "false"
    },
    {
      "tag": "CreateField",
      "model": "User",
      "field": "disabled",
      "type": "Boolean",
      "arity": "Required"
    },
    {
      "tag": "CreateDirective",
      "location": {
        "path": {
          "tag": "Field",
          "model": "User",
          "field": "disabled"
        },
        "directive": "default"
      }
    },
    {
      "tag": "CreateArgument",
      "location": {
        "tag": "Directive",
        "path": {
          "tag": "Field",
          "model": "User",
          "field": "disabled"
        },
        "directive": "default"
      },
      "argument": "",
      "value": "true"
    },
    {
      "tag": "CreateField",
      "model": "User",
      "field": "avator",
      "type": "File",
      "arity": "Optional"
    },
    {
      "tag": "CreateDirective",
      "location": {
        "path": {
          "tag": "Field",
          "model": "User",
          "field": "avator"
        },
        "directive": "relation"
      }
    },
    {
      "tag": "CreateArgument",
      "location": {
        "tag": "Directive",
        "path": {
          "tag": "Field",
          "model": "User",
          "field": "avator"
        },
        "directive": "relation"
      },
      "argument": "fields",
      "value": "[avatorId]"
    },
    {
      "tag": "CreateArgument",
      "location": {
        "tag": "Directive",
        "path": {
          "tag": "Field",
          "model": "User",
          "field": "avator"
        },
        "directive": "relation"
      },
      "argument": "references",
      "value": "[id]"
    },
    {
      "tag": "CreateField",
      "model": "User",
      "field": "avatorId",
      "type": "Int",
      "arity": "Optional"
    },
    {
      "tag": "CreateField",
      "model": "User",
      "field": "role",
      "type": "Role",
      "arity": "Required"
    },
    {
      "tag": "CreateDirective",
      "location": {
        "path": {
          "tag": "Field",
          "model": "User",
          "field": "role"
        },
        "directive": "default"
      }
    },
    {
      "tag": "CreateArgument",
      "location": {
        "tag": "Directive",
        "path": {
          "tag": "Field",
          "model": "User",
          "field": "role"
        },
        "directive": "default"
      },
      "argument": "",
      "value": "USER"
    },
    {
      "tag": "CreateField",
      "model": "User",
      "field": "forms",
      "type": "Form",
      "arity": "List"
    },
    {
      "tag": "CreateField",
      "model": "User",
      "field": "responses",
      "type": "Response",
      "arity": "List"
    },
    {
      "tag": "CreateField",
      "model": "User",
      "field": "createdAt",
      "type": "DateTime",
      "arity": "Required"
    },
    {
      "tag": "CreateDirective",
      "location": {
        "path": {
          "tag": "Field",
          "model": "User",
          "field": "createdAt"
        },
        "directive": "default"
      }
    },
    {
      "tag": "CreateArgument",
      "location": {
        "tag": "Directive",
        "path": {
          "tag": "Field",
          "model": "User",
          "field": "createdAt"
        },
        "directive": "default"
      },
      "argument": "",
      "value": "now()"
    },
    {
      "tag": "CreateField",
      "model": "User",
      "field": "updatedAt",
      "type": "DateTime",
      "arity": "Required"
    },
    {
      "tag": "CreateDirective",
      "location": {
        "path": {
          "tag": "Field",
          "model": "User",
          "field": "updatedAt"
        },
        "directive": "updatedAt"
      }
    },
    {
      "tag": "CreateModel",
      "model": "File"
    },
    {
      "tag": "CreateField",
      "model": "File",
      "field": "id",
      "type": "Int",
      "arity": "Required"
    },
    {
      "tag": "CreateDirective",
      "location": {
        "path": {
          "tag": "Field",
          "model": "File",
          "field": "id"
        },
        "directive": "default"
      }
    },
    {
      "tag": "CreateArgument",
      "location": {
        "tag": "Directive",
        "path": {
          "tag": "Field",
          "model": "File",
          "field": "id"
        },
        "directive": "default"
      },
      "argument": "",
      "value": "autoincrement()"
    },
    {
      "tag": "CreateDirective",
      "location": {
        "path": {
          "tag": "Field",
          "model": "File",
          "field": "id"
        },
        "directive": "id"
      }
    },
    {
      "tag": "CreateField",
      "model": "File",
      "field": "path",
      "type": "String",
      "arity": "Required"
    },
    {
      "tag": "CreateField",
      "model": "File",
      "field": "filename",
      "type": "String",
      "arity": "Optional"
    },
    {
      "tag": "CreateField",
      "model": "File",
      "field": "mimetype",
      "type": "String",
      "arity": "Optional"
    },
    {
      "tag": "CreateField",
      "model": "File",
      "field": "encoding",
      "type": "String",
      "arity": "Optional"
    },
    {
      "tag": "CreateField",
      "model": "File",
      "field": "createdAt",
      "type": "DateTime",
      "arity": "Required"
    },
    {
      "tag": "CreateDirective",
      "location": {
        "path": {
          "tag": "Field",
          "model": "File",
          "field": "createdAt"
        },
        "directive": "default"
      }
    },
    {
      "tag": "CreateArgument",
      "location": {
        "tag": "Directive",
        "path": {
          "tag": "Field",
          "model": "File",
          "field": "createdAt"
        },
        "directive": "default"
      },
      "argument": "",
      "value": "now()"
    },
    {
      "tag": "CreateField",
      "model": "File",
      "field": "updatedAt",
      "type": "DateTime",
      "arity": "Required"
    },
    {
      "tag": "CreateDirective",
      "location": {
        "path": {
          "tag": "Field",
          "model": "File",
          "field": "updatedAt"
        },
        "directive": "updatedAt"
      }
    },
    {
      "tag": "CreateField",
      "model": "File",
      "field": "User",
      "type": "User",
      "arity": "List"
    },
    {
      "tag": "CreateField",
      "model": "File",
      "field": "Form",
      "type": "Form",
      "arity": "Optional"
    },
    {
      "tag": "CreateDirective",
      "location": {
        "path": {
          "tag": "Field",
          "model": "File",
          "field": "Form"
        },
        "directive": "relation"
      }
    },
    {
      "tag": "CreateArgument",
      "location": {
        "tag": "Directive",
        "path": {
          "tag": "Field",
          "model": "File",
          "field": "Form"
        },
        "directive": "relation"
      },
      "argument": "fields",
      "value": "[formId]"
    },
    {
      "tag": "CreateArgument",
      "location": {
        "tag": "Directive",
        "path": {
          "tag": "Field",
          "model": "File",
          "field": "Form"
        },
        "directive": "relation"
      },
      "argument": "references",
      "value": "[id]"
    },
    {
      "tag": "CreateField",
      "model": "File",
      "field": "formId",
      "type": "Int",
      "arity": "Optional"
    },
    {
      "tag": "CreateField",
      "model": "File",
      "field": "Grade",
      "type": "Grade",
      "arity": "Optional"
    },
    {
      "tag": "CreateDirective",
      "location": {
        "path": {
          "tag": "Field",
          "model": "File",
          "field": "Grade"
        },
        "directive": "relation"
      }
    },
    {
      "tag": "CreateArgument",
      "location": {
        "tag": "Directive",
        "path": {
          "tag": "Field",
          "model": "File",
          "field": "Grade"
        },
        "directive": "relation"
      },
      "argument": "fields",
      "value": "[gradeId]"
    },
    {
      "tag": "CreateArgument",
      "location": {
        "tag": "Directive",
        "path": {
          "tag": "Field",
          "model": "File",
          "field": "Grade"
        },
        "directive": "relation"
      },
      "argument": "references",
      "value": "[id]"
    },
    {
      "tag": "CreateField",
      "model": "File",
      "field": "gradeId",
      "type": "Int",
      "arity": "Optional"
    },
    {
      "tag": "CreateField",
      "model": "File",
      "field": "Response",
      "type": "Response",
      "arity": "Optional"
    },
    {
      "tag": "CreateDirective",
      "location": {
        "path": {
          "tag": "Field",
          "model": "File",
          "field": "Response"
        },
        "directive": "relation"
      }
    },
    {
      "tag": "CreateArgument",
      "location": {
        "tag": "Directive",
        "path": {
          "tag": "Field",
          "model": "File",
          "field": "Response"
        },
        "directive": "relation"
      },
      "argument": "fields",
      "value": "[responseId]"
    },
    {
      "tag": "CreateArgument",
      "location": {
        "tag": "Directive",
        "path": {
          "tag": "Field",
          "model": "File",
          "field": "Response"
        },
        "directive": "relation"
      },
      "argument": "references",
      "value": "[id]"
    },
    {
      "tag": "CreateField",
      "model": "File",
      "field": "responseId",
      "type": "Int",
      "arity": "Optional"
    },
    {
      "tag": "CreateField",
      "model": "File",
      "field": "Question",
      "type": "Question",
      "arity": "Optional"
    },
    {
      "tag": "CreateDirective",
      "location": {
        "path": {
          "tag": "Field",
          "model": "File",
          "field": "Question"
        },
        "directive": "relation"
      }
    },
    {
      "tag": "CreateArgument",
      "location": {
        "tag": "Directive",
        "path": {
          "tag": "Field",
          "model": "File",
          "field": "Question"
        },
        "directive": "relation"
      },
      "argument": "fields",
      "value": "[questionId]"
    },
    {
      "tag": "CreateArgument",
      "location": {
        "tag": "Directive",
        "path": {
          "tag": "Field",
          "model": "File",
          "field": "Question"
        },
        "directive": "relation"
      },
      "argument": "references",
      "value": "[id]"
    },
    {
      "tag": "CreateField",
      "model": "File",
      "field": "questionId",
      "type": "Int",
      "arity": "Optional"
    },
    {
      "tag": "CreateField",
      "model": "File",
      "field": "Answer",
      "type": "Answer",
      "arity": "Optional"
    },
    {
      "tag": "CreateDirective",
      "location": {
        "path": {
          "tag": "Field",
          "model": "File",
          "field": "Answer"
        },
        "directive": "relation"
      }
    },
    {
      "tag": "CreateArgument",
      "location": {
        "tag": "Directive",
        "path": {
          "tag": "Field",
          "model": "File",
          "field": "Answer"
        },
        "directive": "relation"
      },
      "argument": "fields",
      "value": "[answerId]"
    },
    {
      "tag": "CreateArgument",
      "location": {
        "tag": "Directive",
        "path": {
          "tag": "Field",
          "model": "File",
          "field": "Answer"
        },
        "directive": "relation"
      },
      "argument": "references",
      "value": "[id]"
    },
    {
      "tag": "CreateField",
      "model": "File",
      "field": "answerId",
      "type": "Int",
      "arity": "Optional"
    },
    {
      "tag": "CreateField",
      "model": "File",
      "field": "Recommendation",
      "type": "Recommendation",
      "arity": "Optional"
    },
    {
      "tag": "CreateDirective",
      "location": {
        "path": {
          "tag": "Field",
          "model": "File",
          "field": "Recommendation"
        },
        "directive": "relation"
      }
    },
    {
      "tag": "CreateArgument",
      "location": {
        "tag": "Directive",
        "path": {
          "tag": "Field",
          "model": "File",
          "field": "Recommendation"
        },
        "directive": "relation"
      },
      "argument": "fields",
      "value": "[recommendationId]"
    },
    {
      "tag": "CreateArgument",
      "location": {
        "tag": "Directive",
        "path": {
          "tag": "Field",
          "model": "File",
          "field": "Recommendation"
        },
        "directive": "relation"
      },
      "argument": "references",
      "value": "[id]"
    },
    {
      "tag": "CreateField",
      "model": "File",
      "field": "recommendationId",
      "type": "Int",
      "arity": "Optional"
    },
    {
      "tag": "CreateModel",
      "model": "Form"
    },
    {
      "tag": "CreateField",
      "model": "Form",
      "field": "id",
      "type": "Int",
      "arity": "Required"
    },
    {
      "tag": "CreateDirective",
      "location": {
        "path": {
          "tag": "Field",
          "model": "Form",
          "field": "id"
        },
        "directive": "default"
      }
    },
    {
      "tag": "CreateArgument",
      "location": {
        "tag": "Directive",
        "path": {
          "tag": "Field",
          "model": "Form",
          "field": "id"
        },
        "directive": "default"
      },
      "argument": "",
      "value": "autoincrement()"
    },
    {
      "tag": "CreateDirective",
      "location": {
        "path": {
          "tag": "Field",
          "model": "Form",
          "field": "id"
        },
        "directive": "id"
      }
    },
    {
      "tag": "CreateField",
      "model": "Form",
      "field": "title",
      "type": "String",
      "arity": "Required"
    },
    {
      "tag": "CreateField",
      "model": "Form",
      "field": "description",
      "type": "String",
      "arity": "Optional"
    },
    {
      "tag": "CreateField",
      "model": "Form",
      "field": "state",
      "type": "State",
      "arity": "Required"
    },
    {
      "tag": "CreateDirective",
      "location": {
        "path": {
          "tag": "Field",
          "model": "Form",
          "field": "state"
        },
        "directive": "default"
      }
    },
    {
      "tag": "CreateArgument",
      "location": {
        "tag": "Directive",
        "path": {
          "tag": "Field",
          "model": "Form",
          "field": "state"
        },
        "directive": "default"
      },
      "argument": "",
      "value": "PENDING"
    },
    {
      "tag": "CreateField",
      "model": "Form",
      "field": "author",
      "type": "User",
      "arity": "Required"
    },
    {
      "tag": "CreateDirective",
      "location": {
        "path": {
          "tag": "Field",
          "model": "Form",
          "field": "author"
        },
        "directive": "relation"
      }
    },
    {
      "tag": "CreateArgument",
      "location": {
        "tag": "Directive",
        "path": {
          "tag": "Field",
          "model": "Form",
          "field": "author"
        },
        "directive": "relation"
      },
      "argument": "fields",
      "value": "[authorId]"
    },
    {
      "tag": "CreateArgument",
      "location": {
        "tag": "Directive",
        "path": {
          "tag": "Field",
          "model": "Form",
          "field": "author"
        },
        "directive": "relation"
      },
      "argument": "references",
      "value": "[uid]"
    },
    {
      "tag": "CreateField",
      "model": "Form",
      "field": "authorId",
      "type": "String",
      "arity": "Required"
    },
    {
      "tag": "CreateField",
      "model": "Form",
      "field": "questions",
      "type": "Question",
      "arity": "List"
    },
    {
      "tag": "CreateField",
      "model": "Form",
      "field": "grades",
      "type": "Grade",
      "arity": "List"
    },
    {
      "tag": "CreateField",
      "model": "Form",
      "field": "responses",
      "type": "Response",
      "arity": "List"
    },
    {
      "tag": "CreateField",
      "model": "Form",
      "field": "attachments",
      "type": "File",
      "arity": "List"
    },
    {
      "tag": "CreateField",
      "model": "Form",
      "field": "createdAt",
      "type": "DateTime",
      "arity": "Required"
    },
    {
      "tag": "CreateDirective",
      "location": {
        "path": {
          "tag": "Field",
          "model": "Form",
          "field": "createdAt"
        },
        "directive": "default"
      }
    },
    {
      "tag": "CreateArgument",
      "location": {
        "tag": "Directive",
        "path": {
          "tag": "Field",
          "model": "Form",
          "field": "createdAt"
        },
        "directive": "default"
      },
      "argument": "",
      "value": "now()"
    },
    {
      "tag": "CreateField",
      "model": "Form",
      "field": "updatedAt",
      "type": "DateTime",
      "arity": "Required"
    },
    {
      "tag": "CreateDirective",
      "location": {
        "path": {
          "tag": "Field",
          "model": "Form",
          "field": "updatedAt"
        },
        "directive": "updatedAt"
      }
    },
    {
      "tag": "CreateModel",
      "model": "Grade"
    },
    {
      "tag": "CreateField",
      "model": "Grade",
      "field": "id",
      "type": "Int",
      "arity": "Required"
    },
    {
      "tag": "CreateDirective",
      "location": {
        "path": {
          "tag": "Field",
          "model": "Grade",
          "field": "id"
        },
        "directive": "default"
      }
    },
    {
      "tag": "CreateArgument",
      "location": {
        "tag": "Directive",
        "path": {
          "tag": "Field",
          "model": "Grade",
          "field": "id"
        },
        "directive": "default"
      },
      "argument": "",
      "value": "autoincrement()"
    },
    {
      "tag": "CreateDirective",
      "location": {
        "path": {
          "tag": "Field",
          "model": "Grade",
          "field": "id"
        },
        "directive": "id"
      }
    },
    {
      "tag": "CreateField",
      "model": "Grade",
      "field": "name",
      "type": "String",
      "arity": "Required"
    },
    {
      "tag": "CreateField",
      "model": "Grade",
      "field": "description",
      "type": "String",
      "arity": "Required"
    },
    {
      "tag": "CreateField",
      "model": "Grade",
      "field": "form",
      "type": "Form",
      "arity": "Required"
    },
    {
      "tag": "CreateDirective",
      "location": {
        "path": {
          "tag": "Field",
          "model": "Grade",
          "field": "form"
        },
        "directive": "relation"
      }
    },
    {
      "tag": "CreateArgument",
      "location": {
        "tag": "Directive",
        "path": {
          "tag": "Field",
          "model": "Grade",
          "field": "form"
        },
        "directive": "relation"
      },
      "argument": "fields",
      "value": "[formId]"
    },
    {
      "tag": "CreateArgument",
      "location": {
        "tag": "Directive",
        "path": {
          "tag": "Field",
          "model": "Grade",
          "field": "form"
        },
        "directive": "relation"
      },
      "argument": "references",
      "value": "[id]"
    },
    {
      "tag": "CreateField",
      "model": "Grade",
      "field": "formId",
      "type": "Int",
      "arity": "Required"
    },
    {
      "tag": "CreateField",
      "model": "Grade",
      "field": "responses",
      "type": "Response",
      "arity": "List"
    },
    {
      "tag": "CreateField",
      "model": "Grade",
      "field": "recommendations",
      "type": "Recommendation",
      "arity": "List"
    },
    {
      "tag": "CreateField",
      "model": "Grade",
      "field": "min",
      "type": "Float",
      "arity": "Required"
    },
    {
      "tag": "CreateField",
      "model": "Grade",
      "field": "max",
      "type": "Float",
      "arity": "Required"
    },
    {
      "tag": "CreateField",
      "model": "Grade",
      "field": "minInclusive",
      "type": "Boolean",
      "arity": "Required"
    },
    {
      "tag": "CreateDirective",
      "location": {
        "path": {
          "tag": "Field",
          "model": "Grade",
          "field": "minInclusive"
        },
        "directive": "default"
      }
    },
    {
      "tag": "CreateArgument",
      "location": {
        "tag": "Directive",
        "path": {
          "tag": "Field",
          "model": "Grade",
          "field": "minInclusive"
        },
        "directive": "default"
      },
      "argument": "",
      "value": "false"
    },
    {
      "tag": "CreateField",
      "model": "Grade",
      "field": "maxInclusive",
      "type": "Boolean",
      "arity": "Required"
    },
    {
      "tag": "CreateDirective",
      "location": {
        "path": {
          "tag": "Field",
          "model": "Grade",
          "field": "maxInclusive"
        },
        "directive": "default"
      }
    },
    {
      "tag": "CreateArgument",
      "location": {
        "tag": "Directive",
        "path": {
          "tag": "Field",
          "model": "Grade",
          "field": "maxInclusive"
        },
        "directive": "default"
      },
      "argument": "",
      "value": "false"
    },
    {
      "tag": "CreateField",
      "model": "Grade",
      "field": "attachments",
      "type": "File",
      "arity": "List"
    },
    {
      "tag": "CreateField",
      "model": "Grade",
      "field": "createdAt",
      "type": "DateTime",
      "arity": "Required"
    },
    {
      "tag": "CreateDirective",
      "location": {
        "path": {
          "tag": "Field",
          "model": "Grade",
          "field": "createdAt"
        },
        "directive": "default"
      }
    },
    {
      "tag": "CreateArgument",
      "location": {
        "tag": "Directive",
        "path": {
          "tag": "Field",
          "model": "Grade",
          "field": "createdAt"
        },
        "directive": "default"
      },
      "argument": "",
      "value": "now()"
    },
    {
      "tag": "CreateField",
      "model": "Grade",
      "field": "updatedAt",
      "type": "DateTime",
      "arity": "Required"
    },
    {
      "tag": "CreateDirective",
      "location": {
        "path": {
          "tag": "Field",
          "model": "Grade",
          "field": "updatedAt"
        },
        "directive": "updatedAt"
      }
    },
    {
      "tag": "CreateModel",
      "model": "Response"
    },
    {
      "tag": "CreateField",
      "model": "Response",
      "field": "id",
      "type": "Int",
      "arity": "Required"
    },
    {
      "tag": "CreateDirective",
      "location": {
        "path": {
          "tag": "Field",
          "model": "Response",
          "field": "id"
        },
        "directive": "default"
      }
    },
    {
      "tag": "CreateArgument",
      "location": {
        "tag": "Directive",
        "path": {
          "tag": "Field",
          "model": "Response",
          "field": "id"
        },
        "directive": "default"
      },
      "argument": "",
      "value": "autoincrement()"
    },
    {
      "tag": "CreateDirective",
      "location": {
        "path": {
          "tag": "Field",
          "model": "Response",
          "field": "id"
        },
        "directive": "id"
      }
    },
    {
      "tag": "CreateField",
      "model": "Response",
      "field": "author",
      "type": "User",
      "arity": "Required"
    },
    {
      "tag": "CreateDirective",
      "location": {
        "path": {
          "tag": "Field",
          "model": "Response",
          "field": "author"
        },
        "directive": "relation"
      }
    },
    {
      "tag": "CreateArgument",
      "location": {
        "tag": "Directive",
        "path": {
          "tag": "Field",
          "model": "Response",
          "field": "author"
        },
        "directive": "relation"
      },
      "argument": "fields",
      "value": "[authorId]"
    },
    {
      "tag": "CreateArgument",
      "location": {
        "tag": "Directive",
        "path": {
          "tag": "Field",
          "model": "Response",
          "field": "author"
        },
        "directive": "relation"
      },
      "argument": "references",
      "value": "[uid]"
    },
    {
      "tag": "CreateField",
      "model": "Response",
      "field": "authorId",
      "type": "String",
      "arity": "Required"
    },
    {
      "tag": "CreateField",
      "model": "Response",
      "field": "form",
      "type": "Form",
      "arity": "Required"
    },
    {
      "tag": "CreateDirective",
      "location": {
        "path": {
          "tag": "Field",
          "model": "Response",
          "field": "form"
        },
        "directive": "relation"
      }
    },
    {
      "tag": "CreateArgument",
      "location": {
        "tag": "Directive",
        "path": {
          "tag": "Field",
          "model": "Response",
          "field": "form"
        },
        "directive": "relation"
      },
      "argument": "fields",
      "value": "[formId]"
    },
    {
      "tag": "CreateArgument",
      "location": {
        "tag": "Directive",
        "path": {
          "tag": "Field",
          "model": "Response",
          "field": "form"
        },
        "directive": "relation"
      },
      "argument": "references",
      "value": "[id]"
    },
    {
      "tag": "CreateField",
      "model": "Response",
      "field": "formId",
      "type": "Int",
      "arity": "Required"
    },
    {
      "tag": "CreateField",
      "model": "Response",
      "field": "answers",
      "type": "Answer",
      "arity": "List"
    },
    {
      "tag": "CreateField",
      "model": "Response",
      "field": "grade",
      "type": "Grade",
      "arity": "Optional"
    },
    {
      "tag": "CreateDirective",
      "location": {
        "path": {
          "tag": "Field",
          "model": "Response",
          "field": "grade"
        },
        "directive": "relation"
      }
    },
    {
      "tag": "CreateArgument",
      "location": {
        "tag": "Directive",
        "path": {
          "tag": "Field",
          "model": "Response",
          "field": "grade"
        },
        "directive": "relation"
      },
      "argument": "fields",
      "value": "[gradeId]"
    },
    {
      "tag": "CreateArgument",
      "location": {
        "tag": "Directive",
        "path": {
          "tag": "Field",
          "model": "Response",
          "field": "grade"
        },
        "directive": "relation"
      },
      "argument": "references",
      "value": "[id]"
    },
    {
      "tag": "CreateField",
      "model": "Response",
      "field": "gradeId",
      "type": "Int",
      "arity": "Optional"
    },
    {
      "tag": "CreateField",
      "model": "Response",
      "field": "attachments",
      "type": "File",
      "arity": "List"
    },
    {
      "tag": "CreateField",
      "model": "Response",
      "field": "state",
      "type": "State",
      "arity": "Required"
    },
    {
      "tag": "CreateDirective",
      "location": {
        "path": {
          "tag": "Field",
          "model": "Response",
          "field": "state"
        },
        "directive": "default"
      }
    },
    {
      "tag": "CreateArgument",
      "location": {
        "tag": "Directive",
        "path": {
          "tag": "Field",
          "model": "Response",
          "field": "state"
        },
        "directive": "default"
      },
      "argument": "",
      "value": "PENDING"
    },
    {
      "tag": "CreateField",
      "model": "Response",
      "field": "createdAt",
      "type": "DateTime",
      "arity": "Required"
    },
    {
      "tag": "CreateDirective",
      "location": {
        "path": {
          "tag": "Field",
          "model": "Response",
          "field": "createdAt"
        },
        "directive": "default"
      }
    },
    {
      "tag": "CreateArgument",
      "location": {
        "tag": "Directive",
        "path": {
          "tag": "Field",
          "model": "Response",
          "field": "createdAt"
        },
        "directive": "default"
      },
      "argument": "",
      "value": "now()"
    },
    {
      "tag": "CreateField",
      "model": "Response",
      "field": "updatedAt",
      "type": "DateTime",
      "arity": "Required"
    },
    {
      "tag": "CreateDirective",
      "location": {
        "path": {
          "tag": "Field",
          "model": "Response",
          "field": "updatedAt"
        },
        "directive": "updatedAt"
      }
    },
    {
      "tag": "CreateModel",
      "model": "Question"
    },
    {
      "tag": "CreateField",
      "model": "Question",
      "field": "id",
      "type": "Int",
      "arity": "Required"
    },
    {
      "tag": "CreateDirective",
      "location": {
        "path": {
          "tag": "Field",
          "model": "Question",
          "field": "id"
        },
        "directive": "default"
      }
    },
    {
      "tag": "CreateArgument",
      "location": {
        "tag": "Directive",
        "path": {
          "tag": "Field",
          "model": "Question",
          "field": "id"
        },
        "directive": "default"
      },
      "argument": "",
      "value": "autoincrement()"
    },
    {
      "tag": "CreateDirective",
      "location": {
        "path": {
          "tag": "Field",
          "model": "Question",
          "field": "id"
        },
        "directive": "id"
      }
    },
    {
      "tag": "CreateField",
      "model": "Question",
      "field": "questionNumber",
      "type": "Int",
      "arity": "Required"
    },
    {
      "tag": "CreateField",
      "model": "Question",
      "field": "question",
      "type": "String",
      "arity": "Required"
    },
    {
      "tag": "CreateField",
      "model": "Question",
      "field": "weight",
      "type": "Float",
      "arity": "Required"
    },
    {
      "tag": "CreateDirective",
      "location": {
        "path": {
          "tag": "Field",
          "model": "Question",
          "field": "weight"
        },
        "directive": "default"
      }
    },
    {
      "tag": "CreateArgument",
      "location": {
        "tag": "Directive",
        "path": {
          "tag": "Field",
          "model": "Question",
          "field": "weight"
        },
        "directive": "default"
      },
      "argument": "",
      "value": "0.0"
    },
    {
      "tag": "CreateField",
      "model": "Question",
      "field": "instruction",
      "type": "String",
      "arity": "Optional"
    },
    {
      "tag": "CreateField",
      "model": "Question",
      "field": "questionType",
      "type": "QuestionType",
      "arity": "Required"
    },
    {
      "tag": "CreateDirective",
      "location": {
        "path": {
          "tag": "Field",
          "model": "Question",
          "field": "questionType"
        },
        "directive": "default"
      }
    },
    {
      "tag": "CreateArgument",
      "location": {
        "tag": "Directive",
        "path": {
          "tag": "Field",
          "model": "Question",
          "field": "questionType"
        },
        "directive": "default"
      },
      "argument": "",
      "value": "BOOLEAN"
    },
    {
      "tag": "CreateField",
      "model": "Question",
      "field": "form",
      "type": "Form",
      "arity": "Required"
    },
    {
      "tag": "CreateDirective",
      "location": {
        "path": {
          "tag": "Field",
          "model": "Question",
          "field": "form"
        },
        "directive": "relation"
      }
    },
    {
      "tag": "CreateArgument",
      "location": {
        "tag": "Directive",
        "path": {
          "tag": "Field",
          "model": "Question",
          "field": "form"
        },
        "directive": "relation"
      },
      "argument": "fields",
      "value": "[formId]"
    },
    {
      "tag": "CreateArgument",
      "location": {
        "tag": "Directive",
        "path": {
          "tag": "Field",
          "model": "Question",
          "field": "form"
        },
        "directive": "relation"
      },
      "argument": "references",
      "value": "[id]"
    },
    {
      "tag": "CreateField",
      "model": "Question",
      "field": "formId",
      "type": "Int",
      "arity": "Required"
    },
    {
      "tag": "CreateField",
      "model": "Question",
      "field": "answers",
      "type": "Answer",
      "arity": "List"
    },
    {
      "tag": "CreateField",
      "model": "Question",
      "field": "attachments",
      "type": "File",
      "arity": "List"
    },
    {
      "tag": "CreateField",
      "model": "Question",
      "field": "createdAt",
      "type": "DateTime",
      "arity": "Required"
    },
    {
      "tag": "CreateDirective",
      "location": {
        "path": {
          "tag": "Field",
          "model": "Question",
          "field": "createdAt"
        },
        "directive": "default"
      }
    },
    {
      "tag": "CreateArgument",
      "location": {
        "tag": "Directive",
        "path": {
          "tag": "Field",
          "model": "Question",
          "field": "createdAt"
        },
        "directive": "default"
      },
      "argument": "",
      "value": "now()"
    },
    {
      "tag": "CreateField",
      "model": "Question",
      "field": "updatedAt",
      "type": "DateTime",
      "arity": "Required"
    },
    {
      "tag": "CreateDirective",
      "location": {
        "path": {
          "tag": "Field",
          "model": "Question",
          "field": "updatedAt"
        },
        "directive": "updatedAt"
      }
    },
    {
      "tag": "CreateModel",
      "model": "Answer"
    },
    {
      "tag": "CreateField",
      "model": "Answer",
      "field": "id",
      "type": "Int",
      "arity": "Required"
    },
    {
      "tag": "CreateDirective",
      "location": {
        "path": {
          "tag": "Field",
          "model": "Answer",
          "field": "id"
        },
        "directive": "default"
      }
    },
    {
      "tag": "CreateArgument",
      "location": {
        "tag": "Directive",
        "path": {
          "tag": "Field",
          "model": "Answer",
          "field": "id"
        },
        "directive": "default"
      },
      "argument": "",
      "value": "autoincrement()"
    },
    {
      "tag": "CreateDirective",
      "location": {
        "path": {
          "tag": "Field",
          "model": "Answer",
          "field": "id"
        },
        "directive": "id"
      }
    },
    {
      "tag": "CreateField",
      "model": "Answer",
      "field": "response",
      "type": "Response",
      "arity": "Required"
    },
    {
      "tag": "CreateDirective",
      "location": {
        "path": {
          "tag": "Field",
          "model": "Answer",
          "field": "response"
        },
        "directive": "relation"
      }
    },
    {
      "tag": "CreateArgument",
      "location": {
        "tag": "Directive",
        "path": {
          "tag": "Field",
          "model": "Answer",
          "field": "response"
        },
        "directive": "relation"
      },
      "argument": "fields",
      "value": "[responseId]"
    },
    {
      "tag": "CreateArgument",
      "location": {
        "tag": "Directive",
        "path": {
          "tag": "Field",
          "model": "Answer",
          "field": "response"
        },
        "directive": "relation"
      },
      "argument": "references",
      "value": "[id]"
    },
    {
      "tag": "CreateField",
      "model": "Answer",
      "field": "responseId",
      "type": "Int",
      "arity": "Required"
    },
    {
      "tag": "CreateField",
      "model": "Answer",
      "field": "question",
      "type": "Question",
      "arity": "Required"
    },
    {
      "tag": "CreateDirective",
      "location": {
        "path": {
          "tag": "Field",
          "model": "Answer",
          "field": "question"
        },
        "directive": "relation"
      }
    },
    {
      "tag": "CreateArgument",
      "location": {
        "tag": "Directive",
        "path": {
          "tag": "Field",
          "model": "Answer",
          "field": "question"
        },
        "directive": "relation"
      },
      "argument": "fields",
      "value": "[questionId]"
    },
    {
      "tag": "CreateArgument",
      "location": {
        "tag": "Directive",
        "path": {
          "tag": "Field",
          "model": "Answer",
          "field": "question"
        },
        "directive": "relation"
      },
      "argument": "references",
      "value": "[id]"
    },
    {
      "tag": "CreateField",
      "model": "Answer",
      "field": "questionId",
      "type": "Int",
      "arity": "Required"
    },
    {
      "tag": "CreateField",
      "model": "Answer",
      "field": "attachments",
      "type": "File",
      "arity": "List"
    },
    {
      "tag": "CreateField",
      "model": "Answer",
      "field": "booleanValue",
      "type": "Boolean",
      "arity": "Optional"
    },
    {
      "tag": "CreateField",
      "model": "Answer",
      "field": "textValue",
      "type": "String",
      "arity": "Optional"
    },
    {
      "tag": "CreateField",
      "model": "Answer",
      "field": "createdAt",
      "type": "DateTime",
      "arity": "Required"
    },
    {
      "tag": "CreateDirective",
      "location": {
        "path": {
          "tag": "Field",
          "model": "Answer",
          "field": "createdAt"
        },
        "directive": "default"
      }
    },
    {
      "tag": "CreateArgument",
      "location": {
        "tag": "Directive",
        "path": {
          "tag": "Field",
          "model": "Answer",
          "field": "createdAt"
        },
        "directive": "default"
      },
      "argument": "",
      "value": "now()"
    },
    {
      "tag": "CreateField",
      "model": "Answer",
      "field": "updatedAt",
      "type": "DateTime",
      "arity": "Required"
    },
    {
      "tag": "CreateDirective",
      "location": {
        "path": {
          "tag": "Field",
          "model": "Answer",
          "field": "updatedAt"
        },
        "directive": "updatedAt"
      }
    },
    {
      "tag": "CreateModel",
      "model": "Recommendation"
    },
    {
      "tag": "CreateField",
      "model": "Recommendation",
      "field": "id",
      "type": "Int",
      "arity": "Required"
    },
    {
      "tag": "CreateDirective",
      "location": {
        "path": {
          "tag": "Field",
          "model": "Recommendation",
          "field": "id"
        },
        "directive": "default"
      }
    },
    {
      "tag": "CreateArgument",
      "location": {
        "tag": "Directive",
        "path": {
          "tag": "Field",
          "model": "Recommendation",
          "field": "id"
        },
        "directive": "default"
      },
      "argument": "",
      "value": "autoincrement()"
    },
    {
      "tag": "CreateDirective",
      "location": {
        "path": {
          "tag": "Field",
          "model": "Recommendation",
          "field": "id"
        },
        "directive": "id"
      }
    },
    {
      "tag": "CreateField",
      "model": "Recommendation",
      "field": "content",
      "type": "String",
      "arity": "Required"
    },
    {
      "tag": "CreateField",
      "model": "Recommendation",
      "field": "attachments",
      "type": "File",
      "arity": "List"
    },
    {
      "tag": "CreateField",
      "model": "Recommendation",
      "field": "grade",
      "type": "Grade",
      "arity": "Required"
    },
    {
      "tag": "CreateDirective",
      "location": {
        "path": {
          "tag": "Field",
          "model": "Recommendation",
          "field": "grade"
        },
        "directive": "relation"
      }
    },
    {
      "tag": "CreateArgument",
      "location": {
        "tag": "Directive",
        "path": {
          "tag": "Field",
          "model": "Recommendation",
          "field": "grade"
        },
        "directive": "relation"
      },
      "argument": "fields",
      "value": "[gradeId]"
    },
    {
      "tag": "CreateArgument",
      "location": {
        "tag": "Directive",
        "path": {
          "tag": "Field",
          "model": "Recommendation",
          "field": "grade"
        },
        "directive": "relation"
      },
      "argument": "references",
      "value": "[id]"
    },
    {
      "tag": "CreateField",
      "model": "Recommendation",
      "field": "gradeId",
      "type": "Int",
      "arity": "Required"
    },
    {
      "tag": "CreateField",
      "model": "Recommendation",
      "field": "createdAt",
      "type": "DateTime",
      "arity": "Required"
    },
    {
      "tag": "CreateDirective",
      "location": {
        "path": {
          "tag": "Field",
          "model": "Recommendation",
          "field": "createdAt"
        },
        "directive": "default"
      }
    },
    {
      "tag": "CreateArgument",
      "location": {
        "tag": "Directive",
        "path": {
          "tag": "Field",
          "model": "Recommendation",
          "field": "createdAt"
        },
        "directive": "default"
      },
      "argument": "",
      "value": "now()"
    },
    {
      "tag": "CreateField",
      "model": "Recommendation",
      "field": "updatedAt",
      "type": "DateTime",
      "arity": "Required"
    },
    {
      "tag": "CreateDirective",
      "location": {
        "path": {
          "tag": "Field",
          "model": "Recommendation",
          "field": "updatedAt"
        },
        "directive": "updatedAt"
      }
    }
  ]
}